{
  "sections": {
    "1630238521e8733446": {
      "type": "image-with-text",
      "blocks": {
        "1630238521e8733446-0": {
          "type": "heading",
          "settings": {
            "heading": "Ecommerce, Digital Marketing e Social media"
          }
        },
        "1630238521e8733446-1": {
          "type": "text",
          "settings": {
            "text": "<p><em>\"Progettiamo esperienze digitali che aiutino gli imprenditori e le loro aziende  a crescere\"<\/em><\/p>"
          }
        },
        "1630238521e8733446-2": {
          "type": "button",
          "settings": {
            "button_label": "👋🏼 Accedi al Canale Telegram!",
            "button_link": "#"
          }
        }
      },
      "block_order": [
        "1630238521e8733446-0",
        "1630238521e8733446-1",
        "1630238521e8733446-2"
      ],
      "settings": {
        "image": "shopify:\/\/shop_images\/1_0aadef30-33cc-4dc3-abbd-964d9cf852d8.png",
        "height": "adapt",
        "color_scheme": "accent-1",
        "layout": "text_first"
      }
    }
  },
  "order": [
    "1630238521e8733446"
  ]
}
